directapps/__init__.py
directapps/access.py
directapps/apps.py
directapps/conf.py
directapps/controllers.py
directapps/decorators.py
directapps/encoders.py
directapps/exceptions.py
directapps/response.py
directapps/shortcuts.py
directapps/urls.py
directapps/utils.py
directapps/version.py
directapps/views.py
directapps/locale/en/LC_MESSAGES/django.mo
directapps/locale/en/LC_MESSAGES/django.po
directapps/locale/ru/LC_MESSAGES/django.mo
directapps/locale/ru/LC_MESSAGES/django.po
django_directapps-0.7.1.dist-info/AUTHORS
django_directapps-0.7.1.dist-info/LICENSE
django_directapps-0.7.1.dist-info/METADATA
django_directapps-0.7.1.dist-info/WHEEL
django_directapps-0.7.1.dist-info/top_level.txt
django_directapps-0.7.1.dist-info/RECORD
